Metadata-Version: 2.1
Name: zahrapackage
Version: 0.3
Summary: just for testing
Author-email: Zahraa123pro@gamil.com
